atai_url_tool/__init__.py
atai_url_tool/cli.py
atai_url_tool/headers.py
atai_url_tool-0.0.1.dist-info/LICENSE
atai_url_tool-0.0.1.dist-info/METADATA
atai_url_tool-0.0.1.dist-info/WHEEL
atai_url_tool-0.0.1.dist-info/entry_points.txt
atai_url_tool-0.0.1.dist-info/top_level.txt
atai_url_tool-0.0.1.dist-info/RECORD
