Metadata-Version: 2.2
Name: atai-url-tool
Version: 0.0.1
Summary: A CLI tool to check a URL's content type and map it to a simplified type.
Home-page: https://github.com/AtomGradient/atai-url-tool
Author: AtomGradient
Author-email: AtomGradient <alex@atomgradient.com>
Project-URL: Homepage, https://github.com/AtomGradient/atai-url-tool
Classifier: Programming Language :: Python :: 3
Classifier: Operating System :: OS Independent
Requires-Python: >=3.6
License-File: LICENSE
Requires-Dist: playwright
Dynamic: author
Dynamic: home-page
Dynamic: requires-python
